marspylib/__init__.py
marspylib/fret/__init__.py
marspylib-0.1.4.data/scripts/launchFiji
marspylib-0.1.4.dist-info/LICENSE.txt
marspylib-0.1.4.dist-info/METADATA
marspylib-0.1.4.dist-info/WHEEL
marspylib-0.1.4.dist-info/top_level.txt
marspylib-0.1.4.dist-info/RECORD
