Metadata-Version: 2.1
Name: marspylib
Version: 0.1.4
Summary: Library containing python Fiji launcher and python functions to interact with Mars Archives
Home-page: https://github.com/duderstadt-lab/marspylib
Author: Karl Duderstadt, Nadia Huisjes, Thomas Retzer
License: UNKNOWN
Platform: any
License-File: LICENSE.txt
Requires-Dist: jpype1 (>=1.3.0)
Requires-Dist: pyimagej
Requires-Dist: scyjava
Requires-Dist: matplotlib
